odoo/addons/stock_location_empty/README.rst
odoo/addons/stock_location_empty/__init__.py
odoo/addons/stock_location_empty/__manifest__.py
odoo/addons/stock_location_empty/i18n/de.po
odoo/addons/stock_location_empty/i18n/fr.po
odoo/addons/stock_location_empty/i18n/stock_location_empty.pot
odoo/addons/stock_location_empty/models/__init__.py
odoo/addons/stock_location_empty/models/stock_location.py
odoo/addons/stock_location_empty/readme/CONTRIBUTORS.rst
odoo/addons/stock_location_empty/readme/CREDITS.rst
odoo/addons/stock_location_empty/readme/DESCRIPTION.rst
odoo/addons/stock_location_empty/static/description/icon.png
odoo/addons/stock_location_empty/static/description/index.html
odoo/addons/stock_location_empty/tests/__init__.py
odoo/addons/stock_location_empty/tests/test_stock_location_empty.py
odoo/addons/stock_location_empty/views/stock.xml
odoo14_addon_stock_location_empty-14.0.1.0.1.dist-info/METADATA
odoo14_addon_stock_location_empty-14.0.1.0.1.dist-info/WHEEL
odoo14_addon_stock_location_empty-14.0.1.0.1.dist-info/top_level.txt
odoo14_addon_stock_location_empty-14.0.1.0.1.dist-info/RECORD
